treebie/node.py
treebie/__init__.py
treebie/chainmap.py
treebie/resolvers.py
treebie/config.py
treebie/exceptions.py
treebie/log_config.py
treebie/syntaxnode/dispatcher.py
treebie/syntaxnode/__init__.py
treebie/syntaxnode/base.py
treebie-0.00.dist-info/RECORD
treebie-0.00.dist-info/METADATA
treebie-0.00.dist-info/metadata.json
treebie-0.00.dist-info/WHEEL
treebie-0.00.dist-info/DESCRIPTION.rst
treebie-0.00.dist-info/top_level.txt
