Metadata-Version: 2.0
Name: treebie
Version: 0.00
Summary: Basic tree node implementation
Home-page: http://twneale.github.com/treebie/
Author: Thom Neale
Author-email: twneale@gmail.com
License: MIT
Platform: any
